mangodb/__init__.py
mangodb/core.py
mangodb/decoder.py
mangodb/encoder.py
mangodb/utils.py
pymangodb-0.1.1.dist-info/licenses/LICENSE
pymangodb-0.1.1.dist-info/METADATA
pymangodb-0.1.1.dist-info/WHEEL
pymangodb-0.1.1.dist-info/top_level.txt
pymangodb-0.1.1.dist-info/RECORD
