Metadata-Version: 2.4
Name: pymangodb
Version: 0.1.1
Summary: A lightweight, dependency-free document database for Python
Home-page: https://github.com/orfeous/mangodb
Author: Gabor Racz
Author-email: Gabor Racz <orfeous@olab.app>
Project-URL: Homepage, https://github.com/orfeous/mangodb
Classifier: Development Status :: 3 - Alpha
Classifier: Intended Audience :: Developers
Classifier: License :: OSI Approved :: MIT License
Classifier: Programming Language :: Python :: 3
Classifier: Programming Language :: Python :: 3.7
Classifier: Programming Language :: Python :: 3.8
Classifier: Programming Language :: Python :: 3.9
Classifier: Programming Language :: Python :: 3.10
Classifier: Operating System :: OS Independent
Requires-Python: >=3.7
License-File: LICENSE
Dynamic: author
Dynamic: home-page
Dynamic: license-file
Dynamic: requires-python
